{
  "id": "economics.international-economics.chapter-01.topic-02",
  "name": "Global Trade",
  "subject": "economics",
  "summary": "Global Trade is a fundamental concept in economics.",
  "definition": "Global Trade is a fundamental concept in economics.",
  "explanation": "Learn about Global Trade and its applications.",
  "prerequisites": [],
  "relatedConcepts": [],
  "visualizationIds": [],
  "quizIds": [],
  "flashcardIds": [],
  "exampleIds": [],
  "exerciseIds": [],
  "difficulty": "beginner",
  "estimatedMinutes": 10,
  "tags": [
    "economics",
    "global-trade"
  ],
  "learningType": "conceptual",
  "whyItMatters": "",
  "memoryHook": ""
}