{
  "id": "biology.cell-biology.chapter-02.topic-06",
  "name": "Membrane Cholesterol",
  "subject": "biology",
  "summary": "Membrane Cholesterol is a fundamental concept in biology.",
  "definition": "Membrane Cholesterol is a fundamental concept in biology.",
  "explanation": "Learn about Membrane Cholesterol and its applications.",
  "prerequisites": [],
  "relatedConcepts": [],
  "visualizationIds": [],
  "quizIds": [],
  "flashcardIds": [],
  "exampleIds": [],
  "exerciseIds": [],
  "difficulty": "beginner",
  "estimatedMinutes": 10,
  "tags": [
    "biology",
    "membrane-cholesterol"
  ],
  "learningType": "conceptual",
  "whyItMatters": "",
  "memoryHook": ""
}